{"_id":{"$oid":"5daf29c57a2dad36ac28f14b"},"country":"US","email":"demouser@bfyo.com","password":"$2a$10$YDlzG2vBlq/OQoqAy/ugRu1p4oUNU9a2FZQUx/5Hl0hFTe18PkXAa","firstName":"Demo","lastName":"User","address1":"123 Main St","city":"Westfield","state":"IN","postalCode":"46033","createdDate":{"$date":"2019-10-22T16:09:41.272Z"},"modifiedDate":{"$date":"2019-10-22T16:09:41.273Z"},"__v":0}
{"_id":{"$oid":"5daf29c57a2dad36ac28f14c"},"country":"US","email":"john.smith@bfyo.com","password":"$2a$10$m1DwgQntXqutSgc8r6PAR.PenQSHO2cCltpu7x9/rassqRpZeadtS","firstName":"John","lastName":"Smith","address1":"123 Main St","city":"Virginia Beach","state":"VA","postalCode":"23456","createdDate":{"$date":"2019-10-22T16:09:41.273Z"},"modifiedDate":{"$date":"2019-10-22T16:09:41.273Z"},"__v":0}
